eprice_pkg/__init__.py
epricepy-0.1.dist-info/LICENSE
epricepy-0.1.dist-info/METADATA
epricepy-0.1.dist-info/WHEEL
epricepy-0.1.dist-info/top_level.txt
epricepy-0.1.dist-info/RECORD
