Metadata-Version: 2.1
Name: epricepy
Version: 0.1
Summary: This package alows the user to get selected e-commerce product's title and price as tuple according to the user's input url.
Home-page: https://github.com/Zero-Autumn/eprice-package
Author: Christ Oliver Lloyd
Author-email: christlloyd.lloyd@gmail.com
License: UNKNOWN
Platform: UNKNOWN
Classifier: Programming Language :: Python :: 3
Classifier: License :: OSI Approved :: MIT License
Classifier: Operating System :: OS Independent
Requires-Python: >=3.6
Requires-Dist: lxml
Requires-Dist: requests
Requires-Dist: beautifulsoup4
